{
  "ok": true,
  "updated_at": "2026-05-03T17:47:46.801Z",
  "fixturesResults": {
    "current_matches": [
      {
        "game_id": 67432,
        "game_date_time": "2026-05-03T19:30:00.000+0530",
        "game_status": {
          "game_status_name": "in play",
          "game_status_id": 1,
          "game_date_time": "2026-05-03T19:30:00.000+0530",
          "toss": {
            "toss_team_id": 772,
            "toss_decision": "Field"
          }
        },
        "match_status": "Gujarat Titans need 11 runs to win from 1.0 overs",
        "toss_status": "Gujarat Titans won the toss and elected to bowl.",
        "teams": [
          {
            "team_id": 63,
            "team_name": "Punjab Kings",
            "team_short_name": "PNK"
          },
          {
            "team_id": 772,
            "team_name": "Gujarat Titans",
            "team_short_name": "GUT"
          }
        ],
        "results": [
          {
            "batting_team_id": 63,
            "score_info": {
              "overs": 20,
              "runs_scored": 163,
              "wickets": 9
            },
            "innings": 1,
            "declared": 0
          },
          {
            "batting_team_id": 772,
            "score_info": {
              "overs": 19,
              "runs_scored": 153,
              "wickets": 6
            },
            "innings": 2,
            "declared": 0
          }
        ],
        "match_name": "Match 46",
        "match_full_name": "Match 46, Ahmedabad, 03 May 2026, IPL",
        "match_center_url": "/cricket/matchcentre/ipl-2026/67432/pnk-vs-gut/#live",
        "comp_name": "ipl-2026"
      }
    ],
    "results": [
      {
        "game_id": 67431,
        "game_date_time": "2026-05-03T15:30:00.000+0530",
        "game_status": {
          "game_status_name": "result",
          "game_status_id": 10,
          "game_date_time": "2026-05-03T15:30:00.000+0530",
          "toss": {
            "toss_team_id": 244,
            "toss_decision": "Bat"
          }
        },
        "match_status": "Kolkata Knight Riders win by 7 wickets",
        "toss_status": "Sunrisers Hyderabad won the toss and elected to bat.",
        "teams": [
          {
            "team_id": 61,
            "team_name": "Kolkata Knight Riders",
            "team_short_name": "KKR"
          },
          {
            "team_id": 244,
            "team_name": "Sunrisers Hyderabad",
            "team_short_name": "SRH"
          }
        ],
        "results": [
          {
            "batting_team_id": 244,
            "score_info": {
              "overs": 19,
              "runs_scored": 165,
              "wickets": 10
            },
            "innings": 1,
            "declared": 0
          },
          {
            "batting_team_id": 61,
            "score_info": {
              "overs": 18.2,
              "runs_scored": 169,
              "wickets": 3
            },
            "innings": 2,
            "declared": 0
          }
        ],
        "match_name": "Match 45",
        "match_full_name": "Match 45, Hyderabad, 03 May 2026, IPL",
        "match_center_url": "/cricket/matchcentre/ipl-2026/67431/kkr-vs-srh/#scorecard",
        "comp_name": "ipl-2026"
      },
      {
        "game_id": 67430,
        "game_date_time": "2026-05-02T19:30:00.000+0530",
        "game_status": {
          "game_status_name": "result",
          "game_status_id": 10,
          "game_date_time": "2026-05-02T19:30:00.000+0530",
          "toss": {
            "toss_team_id": 62,
            "toss_decision": "Bat"
          }
        },
        "match_status": "Chennai Super Kings win by 8 wickets",
        "toss_status": "Mumbai Indians won the toss and elected to bat.",
        "teams": [
          {
            "team_id": 58,
            "team_name": "Chennai Super Kings",
            "team_short_name": "CSK"
          },
          {
            "team_id": 62,
            "team_name": "Mumbai Indians",
            "team_short_name": "MIN"
          }
        ],
        "results": [
          {
            "batting_team_id": 62,
            "score_info": {
              "overs": 20,
              "runs_scored": 159,
              "wickets": 7
            },
            "innings": 1,
            "declared": 0
          },
          {
            "batting_team_id": 58,
            "score_info": {
              "overs": 18.1,
              "runs_scored": 160,
              "wickets": 2
            },
            "innings": 2,
            "declared": 0
          }
        ],
        "match_name": "Match 44",
        "match_full_name": "Match 44, Chennai, 02 May 2026, IPL",
        "match_center_url": "/cricket/matchcentre/ipl-2026/67430/csk-vs-min/#scorecard",
        "comp_name": "ipl-2026"
      },
      {
        "game_id": 67429,
        "game_date_time": "2026-05-01T19:30:00.000+0530",
        "game_status": {
          "game_status_name": "result",
          "game_status_id": 10,
          "game_date_time": "2026-05-01T19:30:00.000+0530",
          "toss": {
            "toss_team_id": 64,
            "toss_decision": "Bat"
          }
        },
        "match_status": "Delhi Capitals win by 7 wickets",
        "toss_status": "Rajasthan Royals won the toss and elected to bat.",
        "teams": [
          {
            "team_id": 60,
            "team_name": "Delhi Capitals",
            "team_short_name": "DCA"
          },
          {
            "team_id": 64,
            "team_name": "Rajasthan Royals",
            "team_short_name": "RJR"
          }
        ],
        "results": [
          {
            "batting_team_id": 64,
            "score_info": {
              "overs": 20,
              "runs_scored": 225,
              "wickets": 6
            },
            "innings": 1,
            "declared": 0
          },
          {
            "batting_team_id": 60,
            "score_info": {
              "overs": 19.1,
              "runs_scored": 226,
              "wickets": 3
            },
            "innings": 2,
            "declared": 0
          }
        ],
        "match_name": "Match 43",
        "match_full_name": "Match 43, Jaipur, 01 May 2026, IPL",
        "match_center_url": "/cricket/matchcentre/ipl-2026/67429/dca-vs-rjr/#scorecard",
        "comp_name": "ipl-2026"
      }
    ],
    "upcoming_matches": [
      {
        "game_id": 67433,
        "game_date_time": "2026-05-04T19:30:00.000+0530",
        "game_status": {
          "game_status_name": "prematch",
          "game_status_id": 0,
          "game_date_time": "2026-05-04T19:30:00.000+0530",
          "toss": {
            "toss_team_id": null,
            "toss_decision": ""
          }
        },
        "match_status": "2026-05-04T19:30:00.000+0530",
        "toss_status": "Teams will be announced at the toss",
        "teams": [
          {
            "team_id": 62,
            "team_name": "Mumbai Indians",
            "team_short_name": "MIN"
          },
          {
            "team_id": 767,
            "team_name": "Lucknow Super Giants",
            "team_short_name": "LSG"
          }
        ],
        "results": [],
        "match_name": "Match 47",
        "match_full_name": "Match 47, Mumbai, 04 May 2026, IPL",
        "match_center_url": "http://www.google.com/calendar/event?action=TEMPLATE&text=min-vs-lsg&dates=20260504T140000Z/20260504T140000Z&details=ipl-2026%2C%20Match%2047&location=Mumbai",
        "comp_name": "ipl-2026"
      },
      {
        "game_id": 67434,
        "game_date_time": "2026-05-05T19:30:00.000+0530",
        "game_status": {
          "game_status_name": "prematch",
          "game_status_id": 0,
          "game_date_time": "2026-05-05T19:30:00.000+0530",
          "toss": {
            "toss_team_id": null,
            "toss_decision": ""
          }
        },
        "match_status": "2026-05-05T19:30:00.000+0530",
        "toss_status": "Teams will be announced at the toss",
        "teams": [
          {
            "team_id": 58,
            "team_name": "Chennai Super Kings",
            "team_short_name": "CSK"
          },
          {
            "team_id": 60,
            "team_name": "Delhi Capitals",
            "team_short_name": "DCA"
          }
        ],
        "results": [],
        "match_name": "Match 48",
        "match_full_name": "Match 48, Delhi, 05 May 2026, IPL",
        "match_center_url": "http://www.google.com/calendar/event?action=TEMPLATE&text=csk-vs-dca&dates=20260505T140000Z/20260505T140000Z&details=ipl-2026%2C%20Match%2048&location=Delhi",
        "comp_name": "ipl-2026"
      }
    ],
    "last_mod_date": "Sun, 03 May 2026 17:45:05 GMT"
  },
  "points": {
    "standings": [
      {
        "teamRecord": [
          {
            "team": 63,
            "team_name": "Punjab Kings",
            "team_short_name": "PNK",
            "position": 1,
            "lost": 1,
            "matchTied": 0,
            "noResult": 1,
            "netRunRate": 1.043,
            "points": 13,
            "won": 6,
            "played": 8
          },
          {
            "team": 57,
            "team_name": "Royal Challengers Bengaluru",
            "team_short_name": "RCB",
            "position": 2,
            "lost": 3,
            "matchTied": 0,
            "noResult": 0,
            "netRunRate": 1.42,
            "points": 12,
            "won": 6,
            "played": 9
          },
          {
            "team": 244,
            "team_name": "Sunrisers Hyderabad",
            "team_short_name": "SRH",
            "position": 3,
            "lost": 4,
            "matchTied": 0,
            "noResult": 0,
            "netRunRate": 0.644,
            "points": 12,
            "won": 6,
            "played": 10
          },
          {
            "team": 64,
            "team_name": "Rajasthan Royals",
            "team_short_name": "RJR",
            "position": 4,
            "lost": 4,
            "matchTied": 0,
            "noResult": 0,
            "netRunRate": 0.51,
            "points": 12,
            "won": 6,
            "played": 10
          },
          {
            "team": 772,
            "team_name": "Gujarat Titans",
            "team_short_name": "GUT",
            "position": 5,
            "lost": 4,
            "matchTied": 0,
            "noResult": 0,
            "netRunRate": -0.192,
            "points": 10,
            "won": 5,
            "played": 9
          },
          {
            "team": 58,
            "team_name": "Chennai Super Kings",
            "team_short_name": "CSK",
            "position": 6,
            "lost": 5,
            "matchTied": 0,
            "noResult": 0,
            "netRunRate": 0.005,
            "points": 8,
            "won": 4,
            "played": 9
          },
          {
            "team": 60,
            "team_name": "Delhi Capitals",
            "team_short_name": "DCA",
            "position": 7,
            "lost": 5,
            "matchTied": 0,
            "noResult": 0,
            "netRunRate": -0.895,
            "points": 8,
            "won": 4,
            "played": 9
          },
          {
            "team": 61,
            "team_name": "Kolkata Knight Riders",
            "team_short_name": "KKR",
            "position": 8,
            "lost": 5,
            "matchTied": 0,
            "noResult": 1,
            "netRunRate": -0.539,
            "points": 7,
            "won": 3,
            "played": 9
          },
          {
            "team": 62,
            "team_name": "Mumbai Indians",
            "team_short_name": "MIN",
            "position": 9,
            "lost": 7,
            "matchTied": 0,
            "noResult": 0,
            "netRunRate": -0.803,
            "points": 4,
            "won": 2,
            "played": 9
          },
          {
            "team": 767,
            "team_name": "Lucknow Super Giants",
            "team_short_name": "LSG",
            "position": 10,
            "lost": 6,
            "matchTied": 0,
            "noResult": 0,
            "netRunRate": -1.106,
            "points": 4,
            "won": 2,
            "played": 8
          }
        ]
      }
    ],
    "updated_date": "2026-05-03T13:33:03.278Z",
    "comp_name": "IPL 2026"
  },
  "players": [
    {
      "_id": "69c810ed2009be257da07d33",
      "total_fours_scored": 1409,
      "total_sixes_scored": 821,
      "top_wicket_takers": [
        {
          "player_id": 4384,
          "bowling_average": 15.53,
          "wickets_taken": 17,
          "player_name": "Bhuvneshwar Kumar"
        },
        {
          "player_id": 12705,
          "bowling_average": 15.82,
          "wickets_taken": 17,
          "player_name": "Anshul Kamboj"
        },
        {
          "player_id": 9855,
          "bowling_average": 21.27,
          "wickets_taken": 15,
          "player_name": "Jofra Archer"
        }
      ],
      "top_run_scorers": [
        {
          "player_id": 11022,
          "runs_scored": 440,
          "balls_faced": 213,
          "player_name": "Abhishek Sharma"
        },
        {
          "player_id": 6698,
          "runs_scored": 433,
          "balls_faced": 233,
          "player_name": "Lokesh Rahul"
        },
        {
          "player_id": 7620,
          "runs_scored": 425,
          "balls_faced": 271,
          "player_name": "Heinrich Klaasen"
        }
      ]
    }
  ],
  "errors": {}
}